AsymmetricEncryptions/__init__.py
AsymmetricEncryptions/Exceptions/Exceptions.py
AsymmetricEncryptions/Exceptions/__init__.py
AsymmetricEncryptions/General/BytesAndInts.py
AsymmetricEncryptions/General/Exportation.py
AsymmetricEncryptions/General/Feistel_sha256.py
AsymmetricEncryptions/General/PowerOf2.py
AsymmetricEncryptions/General/PrimeNumberGen.py
AsymmetricEncryptions/General/XOR.py
AsymmetricEncryptions/General/__init__.py
AsymmetricEncryptions/Interfaces/IEncryptAndDecrypt.py
AsymmetricEncryptions/Interfaces/IExport.py
AsymmetricEncryptions/Interfaces/IKey.py
AsymmetricEncryptions/Interfaces/ISignAndVerify.py
AsymmetricEncryptions/Interfaces/__init__.py
AsymmetricEncryptions/MPC/DiningCryptographers.py
AsymmetricEncryptions/MPC/MPC_Addition.py
AsymmetricEncryptions/MPC/MPC_General.py
AsymmetricEncryptions/MPC/__init__.py
AsymmetricEncryptions/Protocols/AOSRingSignatures.py
AsymmetricEncryptions/Protocols/FSZKP.py
AsymmetricEncryptions/Protocols/Feistel.py
AsymmetricEncryptions/Protocols/GaloisField.py
AsymmetricEncryptions/Protocols/KDF.py
AsymmetricEncryptions/Protocols/OAEP.py
AsymmetricEncryptions/Protocols/OT1O2.py
AsymmetricEncryptions/Protocols/Padding.py
AsymmetricEncryptions/Protocols/RSADH.py
AsymmetricEncryptions/Protocols/RingSignatures.py
AsymmetricEncryptions/Protocols/SSS.py
AsymmetricEncryptions/Protocols/SchnorrPOK.py
AsymmetricEncryptions/Protocols/ThreePass.py
AsymmetricEncryptions/Protocols/YAK.py
AsymmetricEncryptions/Protocols/__init__.py
AsymmetricEncryptions/Protocols/Kerberos/AuthServer.py
AsymmetricEncryptions/Protocols/Kerberos/KDC.py
AsymmetricEncryptions/Protocols/Kerberos/KRBS_Client.py
AsymmetricEncryptions/Protocols/Kerberos/KRBS_Service.py
AsymmetricEncryptions/Protocols/Kerberos/TicketGrantingServer.py
AsymmetricEncryptions/Protocols/Kerberos/__init__.py
AsymmetricEncryptions/PublicPrivateKey/__init__.py
AsymmetricEncryptions/PublicPrivateKey/DLIES/DLIES.py
AsymmetricEncryptions/PublicPrivateKey/DLIES/DLIESKey.py
asymmetric_encryption-0.2.2.dist-info/LICENSE
asymmetric_encryption-0.2.2.dist-info/METADATA
asymmetric_encryption-0.2.2.dist-info/WHEEL
asymmetric_encryption-0.2.2.dist-info/top_level.txt
asymmetric_encryption-0.2.2.dist-info/RECORD
